data/__init__.py
data/data.py
data/entity.py
data/kodifikator.xlsx
test/__init__.py
katottglib-0.2.1.dist-info/LICENSE
katottglib-0.2.1.dist-info/METADATA
katottglib-0.2.1.dist-info/WHEEL
katottglib-0.2.1.dist-info/top_level.txt
katottglib-0.2.1.dist-info/RECORD
