Metadata-Version: 2.1
Name: katottglib
Version: 0.2.1
Summary: A Python lib to operate KATOTTG addresses (classified administrative division of Ukraine).
Home-page: https://github.com/sen-den/katottglib
Author: Denis Senchishen
Author-email: dsenchishen@icloud.com
License: MIT
Classifier: Intended Audience :: Developers
Classifier: License :: OSI Approved :: MIT License
Classifier: Operating System :: OS Independent
Classifier: Programming Language :: Python
Classifier: Programming Language :: Python :: 3
License-File: LICENSE
